[
  {
    "name": "Ancient Orb",
    "base_cost": 1,
    "description": "Enigmatic and extremely old, this is an artifact of the Eternal Forest. It floats in the air by unknown means.",
    "image": "static/images/Ancient_Orb_-_EoW_icon.png",
    "health": null,
    "attack_dmg": null,
    "size": "1 x 1",
    "height": 1,
    "type": "object"
  },
  {
    "name": "Beetle Mound",
    "base_cost": 2,
    "description": "A strange pillar of soil that produces Beetles endlessly or until it's destroyed.",
    "image": "static/images/Beetle_Mound_-_EoW_icon.png",
    "health": null,
    "attack_dmg": null,
    "size": "1 x 1",
    "height": 4,
    "type": "object"
  },
  {
    "name": "Boulder",
    "base_cost": 1,
    "description": "A hard rock that's very heavy, but you can move it if you really push.",
    "image": "static/images/Boulder_-_EoW_icon.png",
    "health": null,
    "attack_dmg": null,
    "size": "1 x 1",
    "height": 2,
    "type": "object"
  },
  {
    "name": "Brazier",
    "base_cost": 2,
    "description": "Stand near this portable fire pit and bask in its warming glow to stave off the cold.",
    "image": "static/images/Brazier_-_EoW_icon.png",
    "health": null,
    "attack_dmg": null,
    "size": "1 x 1",
    "height": 4,
    "type": "object"
  },
  {
    "name": "Carrot",
    "base_cost": 1,
    "description": "Harvested fresh from a field northwest of Hyrule Castle, this carrot is quite sweet. Horses come running for them.",
    "image": "static/images/Carrot_-_EoW_icon.png",
    "health": null,
    "attack_dmg": null,
    "size": "1 x 1",
    "height": 2,
    "type": "object"
  },
  {
    "name": "Cat Statue",
    "base_cost": 1,
    "description": "A lithe statue with a mark on its forehead and rounded features. Its cunning eyes stare into the distance.",
    "image": "static/images/Cat_Statue_-_EoW_icon.png",
    "health": null,
    "attack_dmg": null,
    "size": "1 x 1",
    "height": 4,
    "type": "object"
  },
  {
    "name": "Cloud",
    "base_cost": 2,
    "description": "The Still World has petrified this cloud into something you can stand on for a short while.",
    "image": "static/images/Cloud_-_EoW_icon.png",
    "health": null,
    "attack_dmg": null,
    "size": "1 x 2",
    "height": 1,
    "type": "object"
  },
  {
    "name": "Decorative Shrub",
    "base_cost": 1,
    "description": "An ornamental plant hardy enough to support a person on its bushy leaves.",
    "image": "static/images/Decorative_Shrub_-_EoW_icon.png",
    "health": null,
    "attack_dmg": null,
    "size": "1 x 1",
    "height": 4,
    "type": "object"
  },
  {
    "name": "Elephant Statue",
    "base_cost": 1,
    "description": "An impressive statue with a long trunk and polished tusks. Its knowing eyes stare into the distance.",
    "image": "static/images/Elephant_Statue_-_EoW_icon.png",
    "health": null,
    "attack_dmg": null,
    "size": "1 x 1",
    "height": 4,
    "type": "object"
  },
  {
    "name": "Firework",
    "base_cost": 2,
    "description": "This device, crowning achievement of its Goron artisan, launches three fireworks in a row.",
    "image": "static/images/Firework_-_EoW_icon.png",
    "health": null,
    "attack_dmg": null,
    "size": "1 x 1",
    "height": 2,
    "type": "object"
  },
  {
    "name": "Flying Tile",
    "base_cost": 3,
    "description": "This magical floor tile flies at any who come near. If you stand on top of it, you can briefly fly with it.",
    "image": "static/images/Flying_Tile_-_EoW_icon.png",
    "health": null,
    "attack_dmg": null,
    "size": "1 x 1",
    "height": 1,
    "type": "object"
  },
  {
    "name": "Gerudo Pot",
    "base_cost": 1,
    "description": "A fine pot with vibrant colors to catch the eye. It is typical in Gerudo culture and has been for ages.",
    "image": "static/images/Gerudo_Pot_-_EoW_icon.png",
    "health": null,
    "attack_dmg": null,
    "size": "1 x 1",
    "height": 2,
    "type": "object"
  },
  {
    "name": "Grilled Fish",
    "base_cost": 1,
    "description": "This perfectly grilled, flaky fish can instantly entice certain monsters with its irresistible, savory aroma.",
    "image": "static/images/Grilled_Fish_-_EoW_icon.png",
    "health": null,
    "attack_dmg": null,
    "size": "1 x 1",
    "height": 2,
    "type": "object"
  },
  {
    "name": "Hawk Statue",
    "base_cost": 1,
    "description": "A pointed statue with folded wings and a hooked beak. Its sharp eyes stare into the distance.",
    "image": "static/images/Hawk_Statue_-_EoW_icon.png",
    "health": null,
    "attack_dmg": null,
    "size": "1 x 1",
    "height": 4,
    "type": "object"
  },
  {
    "name": "Hyrule Castle Pot",
    "base_cost": 1,
    "description": "An elegant pot from Hyrule Castle, clearly made with love and great effort.",
    "image": "static/images/Hyrule_Castle_Pot_-_EoW_icon.png",
    "health": null,
    "attack_dmg": null,
    "size": "1 x 1",
    "height": 2,
    "type": "object"
  },
  {
    "name": "Ice Block",
    "base_cost": 1,
    "description": "Like most ice, this block slides when pushed and floats in water. It also melts in the heat, again like most ice.",
    "image": "static/images/Ice_Block_-_EoW_icon.png",
    "health": null,
    "attack_dmg": null,
    "size": "1 x 1",
    "height": 2,
    "type": "object"
  },
  {
    "name": "Lava Rock",
    "base_cost": 4,
    "description": "Eldin Volcano is home to many rocks like this one. It is heat resistant and won't crumble, even in lava.",
    "image": "static/images/Lava_Rock_-_EoW_icon.png",
    "health": null,
    "attack_dmg": null,
    "size": "2 x 2",
    "height": 2,
    "type": "object"
  },
  {
    "name": "Meat",
    "base_cost": 1,
    "description": "A large hunk of bone-in meat that has been restored to glistening. Its dripping juices entice certain monsters.",
    "image": "static/images/Meat_-_EoW_icon.png",
    "health": null,
    "attack_dmg": null,
    "size": "1 x 1",
    "height": 2,
    "type": "object"
  },
  {
    "name": "Old Bed",
    "base_cost": 1,
    "description": "This bed is a bit worn out, but you'll still get sleepy if you lie down on it.",
    "image": "static/images/Old_Bed_-_EoW_icon.png",
    "health": null,
    "attack_dmg": null,
    "size": "1 x 2",
    "height": 1,
    "type": "object"
  },
  {
    "name": "Pot",
    "base_cost": 1,
    "description": "A simple pot of a common type. It is big enough for a person to fit inside.",
    "image": "static/images/Pot_-_EoW_icon.png",
    "health": null,
    "attack_dmg": null,
    "size": "1 x 1",
    "height": 2,
    "type": "object"
  },
  {
    "name": "Rock",
    "base_cost": 1,
    "description": "An ordinary rock that might be found anywhere. Good for throwing.",
    "image": "static/images/Rock_-_EoW_icon.png",
    "health": null,
    "attack_dmg": null,
    "size": "1 x 1",
    "height": 1,
    "type": "object"
  },
  {
    "name": "Rock Roast",
    "base_cost": 1,
    "description": "Considered a Goron delicacy, this meal is beyond the chewing power of the average Hylian.",
    "image": "static/images/Rock_Roast_-_EoW_icon.png",
    "health": null,
    "attack_dmg": null,
    "size": "1 x 1",
    "height": 2,
    "type": "object"
  },
  {
    "name": "Sign",
    "base_cost": 1,
    "description": "A simple sign made of wooden planks. These stand all over Hyrule.",
    "image": "static/images/Sign_-_EoW_icon.png",
    "health": null,
    "attack_dmg": null,
    "size": "1 x 1",
    "height": 2,
    "type": "object"
  },
  {
    "name": "Snake Statue",
    "base_cost": 1,
    "description": "A foreboding statue with a raised head and a coiled tail. Its cold eyes stare into the distance.",
    "image": "static/images/Snake_Statue_-_EoW_icon.png",
    "health": null,
    "attack_dmg": null,
    "size": "1 x 1",
    "height": 4,
    "type": "object"
  },
  {
    "name": "Snowball",
    "base_cost": 2,
    "description": "This large ball of snow rolls quickly downhill. While it's painful to be struck by, it is surprisingly fragile.",
    "image": "static/images/Snowball_-_EoW_icon.png",
    "health": null,
    "attack_dmg": null,
    "size": "2 x 2",
    "height": 4,
    "type": "object"
  },
  {
    "name": "Soft Bed",
    "base_cost": 2,
    "description": "It's easy to just close your eyes and drift away on this soft, well-maintained bed.",
    "image": "static/images/Soft_Bed_-_EoW_icon.png",
    "health": null,
    "attack_dmg": null,
    "size": "1 x 2",
    "height": 1,
    "type": "object"
  },
  {
    "name": "Spiked Roller",
    "base_cost": 4,
    "description": "A large log with many knobbly bits sticking out of it. Rolls downhill until something stops it.",
    "image": "static/images/Spiked_Roller_-_EoW_icon.png",
    "health": null,
    "attack_dmg": 4,
    "size": "5 x 1",
    "height": 2,
    "type": "object"
  },
  {
    "name": "Stuffed Toy",
    "base_cost": 1,
    "description": "A cute little plush guy. For creepy, unknown reasons, ghosts are drawn to it.",
    "image": "static/images/Stuffed_Toy_-_EoW_icon.png",
    "health": null,
    "attack_dmg": null,
    "size": "1 x 1",
    "height": 2,
    "type": "object"
  },
  {
    "name": "Table",
    "base_cost": 1,
    "description": "A small, low table, strong enough for a person to stand on.",
    "image": "static/images/Table_-_EoW_icon.png",
    "health": null,
    "attack_dmg": null,
    "size": "1 x 1",
    "height": 1,
    "type": "object"
  },
  {
    "name": "Trampoline",
    "base_cost": 1,
    "description": "This children's toy of springy cloth on a wooden frame lets you jump higher than usual if you hop onto it.",
    "image": "static/images/Trampoline_-_EoW_icon.png",
    "health": null,
    "attack_dmg": null,
    "size": "1 x 1",
    "height": 1,
    "type": "object"
  },
  {
    "name": "Water Block",
    "base_cost": 1,
    "description": "Liquid in a cube shape. If laid next to others, you can swim through them.",
    "image": "static/images/Water_Block_-_EoW_icon.png",
    "health": null,
    "attack_dmg": null,
    "size": "1 x 1",
    "height": 2,
    "type": "object"
  },
  {
    "name": "Wind Cannon",
    "base_cost": 2,
    "description": "An arcane device that continually blows a strong wind straight ahead that can disperse sand or extinguish flames.",
    "image": "static/images/Wind_Cannon_-_EoW_icon.png",
    "health": null,
    "attack_dmg": null,
    "size": "1 x 1",
    "height": 2,
    "type": "object"
  },
  {
    "name": "Wooden Box",
    "base_cost": 1,
    "description": "A large, wooden box made of planks that is light enough to float on water.",
    "image": "static/images/Wooden_Box_-_EoW_icon.png",
    "health": null,
    "attack_dmg": null,
    "size": "1 x 1",
    "height": 2,
    "type": "object"
  },
  {
    "name": "Zelda's Bed",
    "base_cost": 3,
    "description": "There's no better place to sleep than your own bed from your own castle.",
    "image": "static/images/Zelda's_Bed_-_EoW_icon.png",
    "health": null,
    "attack_dmg": null,
    "size": "1 x 2",
    "height": 1,
    "type": "object"
  },
  {
    "name": "Albatrawl",
    "base_cost": 2,
    "description": "A patient hunter of the air, this monster can suddenly dive, even into the water, to catch its prey.",
    "image": "static/images/Albatrawl_-_EoW_icon.png",
    "health": 8,
    "attack_dmg": 4,
    "size": "1 x 1",
    "height": 2,
    "type": "monster"
  },
  {
    "name": "Armos",
    "base_cost": 2,
    "description": "This living statue tirelessly patrols back and forth in a straight path, never wavering, always facing directly ahead.",
    "image": "static/images/Armos_-_EoW_icon.png",
    "health": 10,
    "attack_dmg": null,
    "size": "1 x 1",
    "height": 4,
    "type": "monster"
  },
  {
    "name": "Aruroda",
    "base_cost": 2,
    "description": "From out of the vast and trackless desert comes this one-eyed menace. It tries to get behind foes to sting them.",
    "image": "static/images/Aruroda_-_EoW_icon.png",
    "health": 10,
    "attack_dmg": 4,
    "size": "1 x 1",
    "height": 2,
    "type": "monster"
  },
  {
    "name": "Baby Gohma",
    "base_cost": 2,
    "description": "This creature slings sticky webs at foes to slow them down. The webs are curiously flammable though.",
    "image": "static/images/Baby_Gohma_-_EoW_icon.png",
    "health": 8,
    "attack_dmg": 4,
    "size": "1 x 1",
    "height": 2,
    "type": "monster"
  },
  {
    "name": "Ball-and-Chain Trooper",
    "base_cost": 4,
    "description": "Armored from head to toe, this mighty monster swings a ball and chain that can shatter some things on impact.",
    "image": "static/images/Ball-and-Chain_Trooper_-_EoW_icon.png",
    "health": 26,
    "attack_dmg": 6,
    "size": "1 x 1",
    "height": 4,
    "type": "monster"
  },
  {
    "name": "Beakon",
    "base_cost": 3,
    "description": "Persistent and loud, this monster follows its prey and calls for nearby allies to attack on its behalf.",
    "image": "static/images/Beakon_-_EoW_icon.png",
    "health": 18,
    "attack_dmg": null,
    "size": "1 x 1",
    "height": 2,
    "type": "monster"
  },
  {
    "name": "Beamos",
    "base_cost": 3,
    "description": "Any foe in this strange creature's field of vision will be struck by its eyebeams. Under threat, it hardens like rock.",
    "image": "static/images/Beamos_-_EoW_icon.png",
    "health": 1,
    "attack_dmg": 7,
    "size": "1 x 1",
    "height": 2,
    "type": "monster"
  },
  {
    "name": "Beetle",
    "base_cost": 1,
    "description": "This small monster isn't very strong but can overwhelm the unwary in great numbers.",
    "image": "static/images/Beetle_-_EoW_icon.png",
    "health": 1,
    "attack_dmg": 2,
    "size": "1 x 1",
    "height": 2,
    "type": "monster"
  },
  {
    "name": "Bio Deku Baba",
    "base_cost": 3,
    "description": "Capable of swallowing whole anything that approaches it, this fearsome plant is vulnerable to having its head pulled.",
    "image": "static/images/Bio_Deku_Baba_-_EoW_icon.png",
    "health": 24,
    "attack_dmg": 6,
    "size": "1 x 1",
    "height": 4,
    "type": "monster"
  },
  {
    "name": "Biri",
    "base_cost": 2,
    "description": "Electrically charged, this floating creature zaps an area around itself. Its field reaches further in water.",
    "image": "static/images/Biri_-_EoW_icon.png",
    "health": 4,
    "attack_dmg": 1,
    "size": "1 x 1",
    "height": 2,
    "type": "monster"
  },
  {
    "name": "Bombfish",
    "base_cost": 4,
    "description": "This dangerous fish explodes at the slightest impact and is capable of breaking weakened walls.",
    "image": "static/images/Bombfish_-_EoW_icon.png",
    "health": 1,
    "attack_dmg": 12,
    "size": "1 x 1",
    "height": 2,
    "type": "monster"
  },
  {
    "name": "Boomerang Boarblin",
    "base_cost": 2,
    "description": "Trained in the use of boomerangs, this Boarblin warrior is dangerous both coming and going.",
    "image": "static/images/Boomerang_Boarblin_-_EoW_icon.png",
    "health": 10,
    "attack_dmg": 4,
    "size": "1 x 1",
    "height": 2,
    "type": "monster"
  },
  {
    "name": "Boomerang Boarblin Lv. 2",
    "base_cost": 4,
    "description": "Having mastered the boomerang, this Boarblin has deadly aim. Its sharpened boomerangs are quick and accurate.",
    "image": "static/images/Boomerang_Boarblin_Lv_2_-_EoW_icon.png",
    "health": 29,
    "attack_dmg": 8,
    "size": "1 x 1",
    "height": 2,
    "type": "monster"
  },
  {
    "name": "Buzz Blob",
    "base_cost": 3,
    "description": "Slow-moving but powerfully charged with electricity, this creature's shock field is even wider in water.",
    "image": "static/images/Buzz_Blob_-_EoW_icon.png",
    "health": 12,
    "attack_dmg": 3,
    "size": "1 x 1",
    "height": 2,
    "type": "monster"
  },
  {
    "name": "Caromadillo",
    "base_cost": 2,
    "description": "This monster lives in the caves or on plains, recklessly charging everything it sees. It holds its tail to roll, bouncing off walls.",
    "image": "static/images/Caromadillo_-_EoW_icon.png",
    "health": 12,
    "attack_dmg": 4,
    "size": "1 x 1",
    "height": 2,
    "type": "monster"
  },
  {
    "name": "Caromadillo Lv. 2",
    "base_cost": 3,
    "description": "A powerful monster that hurls itself with incredible momentum, flying over holes with ease.",
    "image": "static/images/Caromadillo_Lv_2_-_EoW_icon.png",
    "health": 24,
    "attack_dmg": 8,
    "size": "1 x 1",
    "height": 2,
    "type": "monster"
  },
  {
    "name": "Chompfin",
    "base_cost": 4,
    "description": "This jagged-toothed bully rules the water, chomping and spinning with a slap of its tail.",
    "image": "static/images/Chompfin_-_EoW_icon.png",
    "health": 36,
    "attack_dmg": 12,
    "size": "1 x 2",
    "height": 2,
    "type": "monster"
  },
  {
    "name": "Club Boarblin",
    "base_cost": 2,
    "description": "A brute of the northern Gerudo Desert, this creature bounds directly at foes and lays into them with its club.",
    "image": "static/images/Club_Boarblin_-_EoW_icon.png",
    "health": 12,
    "attack_dmg": 4,
    "size": "1 x 1",
    "height": 2,
    "type": "monster"
  },
  {
    "name": "Club Boarblin Lv. 2",
    "base_cost": 4,
    "description": "This desert-dwelling warrior wields a club and shield. Fiercely territorial, it will pursue intruders doggedly.",
    "image": "static/images/Club_Boarblin_Lv_2_-_EoW_icon.png",
    "health": 29,
    "attack_dmg": 9,
    "size": "1 x 1",
    "height": 2,
    "type": "monster"
  },
  {
    "name": "Crow",
    "base_cost": 2,
    "description": "Roosting in high-up spots, this bird monster swoops down to seal people's rupees.",
    "image": "static/images/Crow_-_EoW_icon.png",
    "health": 9,
    "attack_dmg": 4,
    "size": "1 x 1",
    "height": 2,
    "type": "monster"
  },
  {
    "name": "Darknut",
    "base_cost": 3,
    "description": "A martial monster in sturdy armor. It is slow and plodding, but its armor makes it utterly immune to blunt-force attacks.",
    "image": "static/images/Darknut_-_EoW_icon.png",
    "health": 18,
    "attack_dmg": 6,
    "size": "1 x 1",
    "height": 2,
    "type": "monster"
  },
  {
    "name": "Darknut Lv. 2",
    "base_cost": 4,
    "description": "This elite monster wears bright armor that protects against most attacks. Its powerful axe cleaves through foes.",
    "image": "static/images/Darknut_Lv_2_-_EoW_icon.png",
    "health": 34,
    "attack_dmg": 12,
    "size": "1 x 1",
    "height": 2,
    "type": "monster"
  },
  {
    "name": "Darknut Lv. 3",
    "base_cost": 5,
    "description": "Huge and powerful, this Darknut variant wears armor that can even protect it from arrows.",
    "image": "static/images/Darknut_Lv_3_-_EoW_icon.png",
    "health": 45,
    "attack_dmg": 19,
    "size": "1 x 1",
    "height": 2,
    "type": "monster"
  },
  {
    "name": "Deku Baba",
    "base_cost": 2,
    "description": "Aggressive and immobile, this plant reaches for anything that gets near. It is vulnerable to having its head pulled.",
    "image": "static/images/Deku_Baba_-_EoW_icon.png",
    "health": 12,
    "attack_dmg": 3,
    "size": "1 x 1",
    "height": 4,
    "type": "monster"
  },
  {
    "name": "Deku Baba Lv. 2",
    "base_cost": 3,
    "description": "A ferocious plant that uses its large mouth to snap at and swallow enemies. Its hard head protects it from attacks.",
    "image": "static/images/Deku_Baba_Lv_2_-_EoW_icon.png",
    "health": 24,
    "attack_dmg": 6,
    "size": "1 x 1",
    "height": 4,
    "type": "monster"
  },
  {
    "name": "Drippitune",
    "base_cost": 3,
    "description": "This amphibious monster's croaking song can call rain from a cloudless sky.",
    "image": "static/images/Drippitune_-_EoW_icon.png",
    "health": 12,
    "attack_dmg": 0,
    "size": "1 x 1",
    "height": 2,
    "type": "monster"
  },
  {
    "name": "Electric Keese",
    "base_cost": 4,
    "description": "Wreathed in electricity, this flying monster shocks and paralyzes any foe it touches. Its field reaches further in water.",
    "image": "static/images/Electric_Keese_-_EoW_icon.png",
    "health": 8,
    "attack_dmg": 3,
    "size": "1 x 1",
    "height": 2,
    "type": "monster"
  },
    {
    "name": "Electric Wizzrobe",
    "base_cost": 5,
    "description": "A potent electricity wielder, this creature warps across the sky, firing lightning-fast bolts that shock targets.",
    "image": "static/images/Electric_Wizzrobe_-_EoW_icon.png",
    "health": 38,
    "attack_dmg": 12,
    "size": "1 x 1",
    "height": 2,
    "type": "monster"
  },
    {
    "name": "Fire Keese",
    "base_cost": 4,
    "description": "This flying monster burns hot enough to ignite anything it touches but will be destroyed by a stiff wind.",
    "image": "static/images/Fire_Keese_-_EoW_icon.png",
    "health": 8,
    "attack_dmg": 3,
    "size": "1 x 1",
    "height": 2,
    "type": "monster"
  },
    {
    "name": "Fire Octo",
    "base_cost": 2,
    "description": "This Octorok variety has adapted to its volcanic habitat, using its high internal temperature to spit fiery rocks.",
    "image": "static/images/Fire_Octo_-_EoW_icon.png",
    "health": 10,
    "attack_dmg": 3,
    "size": "1 x 1",
    "height": 2,
    "type": "monster"
  },
  {
    "name": "Fire Wizzrobe",
    "base_cost": 5,
    "description": "This Wizzrobe variety has adapted to its volcanic habitat, using its high internal temperature to toss flaming slashes.",
    "image": "static/images/Fire_Wizzrobe_-_EoW_icon.png",
    "health": 38,
    "attack_dmg": 12,
    "size": "1 x 1",
    "height": 2,
    "type": "monster"
  },  {
    "name": "Freezard",
    "base_cost": 3,
    "description": "On spotting an enemy, this monster will blow out icy breath as it implacably pursues its quarry.",
    "image": "static/images/Freezard_-_EoW_icon.png",
    "health": 19,
    "attack_dmg": 1,
    "size": "1 x 1",
    "height": 2,
    "type": "monster"
  },
   {
    "name": "Freeze Slug",
    "base_cost": 3,
    "description": "Lurking on the walls and floors of the coldest places, this creature leaves a path of freezing ice behind it.",
    "image": "static/images/Freeze_Slug_-_EoW_icon.png",
    "health": 19,
    "attack_dmg": 6,
    "size": "1 x 1",
    "height": 2,
    "type": "monster"
  },
   {
    "name": "Ghini",
    "base_cost": 1,
    "description": "Eternally lonely, this one-eyed ghost has an unfortunate tendency to lick potential friends.",
    "image": "static/images/Ghini_-_EoW_icon.png",
    "health": 1,
    "attack_dmg": 2,
    "size": "1 x 1",
    "height": 2,
    "type": "monster"
  },
     {
    "name": "Ghini Lv. 2",
    "base_cost": 3,
    "description": "The largest type of Ghini, this monster has a huge eyeball and tongue to match its stature.",
    "image": "static/images/Ghini_Lv_2_-_EoW_icon.png",
    "health": 18,
    "attack_dmg": 8,
    "size": "1 x 1",
    "height": 2,
    "type": "monster"
  },
     {
    "name": "Ghirro",
    "base_cost": 2,
    "description": "This airborne pest hinders foes with its powerful breath. The gale is strong enough to shove a person around.",
    "image": "static/images/Ghirro_-_EoW_icon.png",
    "health": 4,
    "attack_dmg": null,
    "size": "1 x 1",
    "height": 2,
    "type": "monster"
  },
     {
    "name": "Giant Goponga Flower",
    "base_cost": 4,
    "description": "Native to the Faron Wetlands, this monstrous plant spits large clusters of dangerous pollen at enemies.",
    "image": "static/images/Giant_Goponga_Flower_-_EoW_icon.png",
    "health": 36,
    "attack_dmg": 11,
    "size": "2 x 2",
    "height": 4,
    "type": "monster"
  },
     {
    "name": "Gibdo",
    "base_cost": 3,
    "description": "A bandaged monster that can stop foes in their tracks. It is weak to fire, though, and will flee in a panic if exposed to it.",
    "image": "static/images/Gibdo_-_EoW_icon.png",
    "health": 30,
    "attack_dmg": 8,
    "size": "1 x 1",
    "height": 2,
    "type": "monster"
  },
     {
    "name": "Gibdo Lv. 2",
    "base_cost": 3,
    "description": "Terrifying and driven by vengeance, this bandaged horror transforms into a ReDead when set on fire.",
    "image": "static/images/Gibdo_Lv_2_-_EoW_icon.png",
    "health": 45,
    "attack_dmg": 12,
    "size": "1 x 1",
    "height": 2,
    "type": "monster"
  },
     {
    "name": "Goo Specter",
    "base_cost": 3,
    "description": "A gooey nightmare that flattens itself to the ground, making it impossible to attack.",
    "image": "static/images/Goo_Specter_-_EoW_icon.png",
    "health": 19,
    "attack_dmg": 8,
    "size": "1 x 1",
    "height": 2,
    "type": "monster"
  },
     {
    "name": "Guay",
    "base_cost": 3,
    "description": "Soaring implacably above Hyrule Field, this winged monster dives to attack prey with its sharp beak.",
    "image": "static/images/Guay_-_EoW_icon.png",
    "health": 18,
    "attack_dmg": 8,
    "size": "1 x 1",
    "height": 2,
    "type": "monster"
  },
     {
    "name": "Gustmaster",
    "base_cost": 3,
    "description": "Entirely immobile, this unusual creature intermittently blows gusts of air strong enough to lift a person off their feet.",
    "image": "static/images/Gustmaster_-_EoW_icon.png",
    "health": 12,
    "attack_dmg": null,
    "size": "1 x 1",
    "height": 2,
    "type": "monster"
  },
     {
    "name": "Hoarder",
    "base_cost": 3,
    "description": "Naturally camouflaged, this creature hides underground until an unwary foe approaches the mushrooms on its back.",
    "image": "static/images/Hoarder_-_EoW_icon.png",
    "health": 24,
    "attack_dmg": 8,
    "size": "1 x 1",
    "height": 4,
    "type": "monster"
  },     {
    "name": "Holmill",
    "base_cost": 3,
    "description": "This monster digs holes in soft earth. Sometimes these holes can be entrances to hard-to-reach places.",
    "image": "static/images/Holmill_-_EoW_icon.png",
    "health": 15,
    "attack_dmg": 7,
    "size": "1 x 1",
    "height": 2,
    "type": "monster"
  },     {
    "name": "Hydrozol",
    "base_cost": 2,
    "description": "A Zol variant that grows when exposed to water. Its liquid surface makes it immune to fire.",
    "image": "static/images/Hydrozol_-_EoW_icon.png",
    "health": 6,
    "attack_dmg": 4,
    "size": "1 x 1",
    "height": 2,
    "type": "monster"
  },
      {
    "name": "Ice Keese",
    "base_cost": 4,
    "description": "A flying monster shrouded in a zone of frigid air that can freeze enemies solid.",
    "image": "static/images/Ice_Keese_-_EoW_icon.png",
    "health": 8,
    "attack_dmg": 3,
    "size": "1 x 1",
    "height": 2,
    "type": "monster"
  },
      {
    "name": "Ice Wizzrobe",
    "base_cost": 5,
    "description": "A mighty caster of ice magic, this creature warps across the sky, freezing enemies with frigid blasts.",
    "image": "static/images/Ice_Wizzrobe_-_EoW_icon.png",
    "health": 38,
    "attack_dmg": 12,
    "size": "1 x 1",
    "height": 2,
    "type": "monster"
  },
      {
    "name": "Ignizol",
    "base_cost": 2,
    "description": "A white Zol with a flame on top of it. Anything it touches is set ablaze.",
    "image": "static/images/Ignizol_-_EoW_icon.png",
    "health": 6,
    "attack_dmg": 4,
    "size": "1 x 1",
    "height": 2,
    "type": "monster"
  },
      {
    "name": "Keese",
    "base_cost": 1,
    "description": "A monster resembling a bat. If you hold one aloft and step off a ledge, you can glide a bit.",
    "image": "static/images/Keese_-_EoW_icon.png",
    "health": 1,
    "attack_dmg": 2,
    "size": "1 x 1",
    "height": 2,
    "type": "monster"
  },
      {
    "name": "Leever",
    "base_cost": 2,
    "description": "A patient, subterranean monster, it waits for prey, then bursts to the surface, rotating its blades to attack.",
    "image": "static/images/Leever_-_EoW_icon.png",
    "health": 12,
    "attack_dmg": 4,
    "size": "1 x 1",
    "height": 2,
    "type": "monster"
  },
      {
    "name": "Lizalfos",
    "base_cost": 3,
    "description": "A hunter by nature, this creature wields a razor-sharp spear. It stabs prey with blinding speed.",
    "image": "static/images/Lizalfos_-_EoW_icon.png",
    "health": 14,
    "attack_dmg": 6,
    "size": "1 x 1",
    "height": 2,
    "type": "monster"
  },
      {
    "name": "Lizalfos Lv. 2",
    "base_cost": 4,
    "description": "Nimble and lizard-like, this creature is resistant to fire and able to leap into close combat from great distances.",
    "image": "static/images/Lizalfos_Lv_2-_EoW_icon.png",
    "health": 20,
    "attack_dmg": 10,
    "size": "1 x 1",
    "height": 2,
    "type": "monster"
  }, {
    "name": "Lizalfos Lv. 3",
    "base_cost": 5,
    "description": "This massive Lizalfos is native to the Faron Wetlands. It is resistant to fire and is also at home underwater.",
    "image": "static/images/Lizalfos_Lv_3_-_EoW_icon.png",
    "health": 30,
    "attack_dmg": 14,
    "size": "2 x 2",
    "height": 2,
    "type": "monster"
  }                                           }
]
